{"id":"tt0103519","title":"The Real West","originalTitle":"","fullTitle":"The Real West (TV Series 1992– )","type":"TVSeries","year":"1992","image":"https://imdb-api.com/images/original/MV5BMjA1MDA3ODAyNF5BMl5BanBnXkFtZTcwMjkxNTEzMQ@@._V1_Ratio0.6751_AL_.jpg","releaseDate":"1993-07-08","runtimeMins":null,"runtimeStr":null,"plot":"This documentary series, which was made in 1992, shows stories of how the real West was created and separates fact from fiction. Hosted by Kenny Rogers","plotLocal":"","plotLocalIsRtl":false,"awards":"Awards, 1 win","directors":"","directorList":[],"writers":"","writerList":[],"stars":"Kenny Rogers, Paul A. Hutton, Robert Utley","starList":[{"id":"nm0737006","name":"Kenny Rogers"},{"id":"nm0404657","name":"Paul A. Hutton"},{"id":"nm1200623","name":"Robert Utley"}],"actorList":[{"id":"nm0737006","image":"https://imdb-api.com/images/original/MV5BMjA0NDA2ODM0M15BMl5BanBnXkFtZTYwNzI2NjQ0._V1_Ratio1.0000_AL_.jpg","name":"Kenny Rogers","asCharacter":"Self - Hostas Self - Host"},{"id":"nm0404657","image":"https://imdb-api.com/images/original/nopicture.jpg","name":"Paul A. Hutton","asCharacter":"Selfas Self…"},{"id":"nm1200623","image":"https://imdb-api.com/images/original/nopicture.jpg","name":"Robert Utley","asCharacter":"Selfas Self…"},{"id":"nm2836586","image":"https://imdb-api.com/images/original/nopicture.jpg","name":"Leon Metz","asCharacter":"Selfas Self…"},{"id":"nm1201411","image":"https://imdb-api.com/images/original/nopicture.jpg","name":"Dee Brown","asCharacter":"Selfas Self"},{"id":"nm2258657","image":"https://imdb-api.com/images/original/nopicture.jpg","name":"Roger McGrath","asCharacter":"Selfas Self…"},{"id":"nm1625446","image":"https://imdb-api.com/images/original/nopicture.jpg","name":"Stephen L. Hardin","asCharacter":"Selfas Self"},{"id":"nm5969840","image":"https://imdb-api.com/images/original/nopicture.jpg","name":"Towana Spivey","asCharacter":"Curator, Ft. Sill Museumas Curator, Ft. Sill Museum…"},{"id":"nm9586272","image":"https://imdb-api.com/images/original/nopicture.jpg","name":"Jay Van Orden","asCharacter":"Selfas Self…"},{"id":"nm5964386","image":"https://imdb-api.com/images/original/nopicture.jpg","name":"Isaac Dog Eagle","asCharacter":"Selfas Self…"},{"id":"nm7363881","image":"https://imdb-api.com/images/original/nopicture.jpg","name":"Art Burton","asCharacter":"Selfas Self"},{"id":"nm2465630","image":"https://imdb-api.com/images/original/nopicture.jpg","name":"Winston Roche","asCharacter":"Selfas Self"},{"id":"nm0949779","image":"https://imdb-api.com/images/original/nopicture.jpg","name":"Kevin R. Young","asCharacter":"Selfas Self"},{"id":"nm2836461","image":"https://imdb-api.com/images/original/nopicture.jpg","name":"Richard Maxwell Brown","asCharacter":"Selfas Self"},{"id":"nm2378703","image":"https://imdb-api.com/images/original/nopicture.jpg","name":"Paul Fees","asCharacter":"Selfas Self"},{"id":"nm1954728","image":"https://imdb-api.com/images/original/nopicture.jpg","name":"Joseph M. Marshall","asCharacter":"Selfas Self"},{"id":"nm1550695","image":"https://imdb-api.com/images/original/nopicture.jpg","name":"Joe Medicine Crow","asCharacter":"Selfas Self…"},{"id":"nm4563253","image":"https://imdb-api.com/images/original/nopicture.jpg","name":"Johnson Holy Rock","asCharacter":"Selfas Self…"}],"fullCast":null,"genres":"Documentary, Western","genreList":[{"key":"Documentary","value":"Documentary"},{"key":"Western","value":"Western"}],"companies":"","companyList":[],"countries":"USA","countryList":[{"key":"USA","value":"USA"}],"languages":"English","languageList":[{"key":"English","value":"English"}],"contentRating":null,"imDbRating":"8","imDbRatingVotes":"92","metacriticRating":null,"ratings":null,"wikipedia":null,"posters":null,"images":null,"trailer":null,"boxOffice":{"budget":"","openingWeekendUSA":"","grossUSA":"","cumulativeWorldwideGross":""},"tagline":null,"keywords":"chiricahua apache,apache indian,arizona territory,apache territory,arizona","keywordList":["chiricahua apache","apache indian","arizona territory","apache territory","arizona"],"similars":[{"id":"tt0409572","title":"Into the West","image":"https://imdb-api.com/images/original/MV5BMTI1NTg4NTE2M15BMl5BanBnXkFtZTcwMzUwNjAzMQ@@._V1_Ratio0.7536_AL_.jpg","imDbRating":"8.0"}],"tvSeriesInfo":{"yearEnd":"","creators":"Craig Haffner, Yann Debonne","creatorList":[{"id":"nm0353121","name":"Craig Haffner"},{"id":"nm0213486","name":"Yann Debonne"}],"seasons":["1","2","3"]},"tvEpisodeInfo":null,"errorMessage":null}
