{"id":"tt1046687","title":"Adventure Special","originalTitle":"","fullTitle":"Adventure Special (TV Episode 1997)","type":"TVEpisode","year":"1997","image":"https://imdb-api.com/images/original/nopicture.jpg","releaseDate":"1997-11-11","runtimeMins":null,"runtimeStr":null,"plot":"","plotLocal":"","plotLocalIsRtl":false,"awards":"","directors":"","directorList":[],"writers":"","writerList":[],"stars":"SuChin Pak","starList":[{"id":"nm0657076","name":"SuChin Pak"}],"actorList":[{"id":"nm0657076","image":"https://imdb-api.com/images/original/MV5BMTc1ODU5OTUwNF5BMl5BanBnXkFtZTYwODk3OTEz._V1_Ratio1.0000_AL_.jpg","name":"SuChin Pak","asCharacter":"Self - Co-Hostas Self - Co-Host"}],"fullCast":null,"genres":"Talk-Show","genreList":[{"key":"Talk-Show","value":"Talk-Show"}],"companies":"KTCA Minneapolis","companyList":[{"id":"co0106797","name":"KTCA Minneapolis"}],"countries":"","countryList":[],"languages":"","languageList":[],"contentRating":null,"imDbRating":null,"imDbRatingVotes":null,"metacriticRating":null,"ratings":null,"wikipedia":null,"posters":null,"images":null,"trailer":null,"boxOffice":{"budget":"","openingWeekendUSA":"","grossUSA":"","cumulativeWorldwideGross":""},"tagline":null,"keywords":"","keywordList":[],"similars":[],"tvSeriesInfo":null,"tvEpisodeInfo":{"seriesId":"tt0131678","seriesTitle":"Newton's Apple","seriesFullTitle":"Newton's Apple (TV Series 1983–1998)","seriesYear":"1983","seriesYearEnd":"1998","seasonNumber":"15","episodeNumber":"7","previousEpisodeId":"tt1046695","nextEpisodeId":"tt1046694"},"errorMessage":null}
