{"id":"tt1047805","title":"Attack of the Killer Metal Man from the Dimensions of the Unknown","originalTitle":"","fullTitle":"Attack of the Killer Metal Man from the Dimensions of the Unknown (2007)","type":"Movie","year":"2007","image":"https://imdb-api.com/images/original/MV5BMWNkMWIxMTItNjQxNy00MjIwLThmMzYtMzJlODJmYzg2MzQ5XkEyXkFqcGdeQXVyMTA5NzI2MQ@@._V1_Ratio0.6751_AL_.jpg","releaseDate":"2007-04-20","runtimeMins":"PT3M","runtimeStr":"PT3M","plot":"","plotLocal":"","plotLocalIsRtl":false,"awards":"","directors":"Jordan Gibson","directorList":[{"id":"nm2677600","name":"Jordan Gibson"}],"writers":"Jordan Gibson","writerList":[{"id":"nm2677600","name":"Jordan Gibson"}],"stars":"Alexandra Schultze, Ryan Blue, Thomas Fix","starList":[{"id":"nm2680565","name":"Alexandra Schultze"},{"id":"nm2683686","name":"Ryan Blue"},{"id":"nm2681217","name":"Thomas Fix"}],"actorList":[{"id":"nm2680565","image":"https://imdb-api.com/images/original/nopicture.jpg","name":"Alexandra Schultze","asCharacter":"Girl on Dateas Girl on Date"},{"id":"nm2683686","image":"https://imdb-api.com/images/original/nopicture.jpg","name":"Ryan Blue","asCharacter":"Boy on Dateas Boy on Date"},{"id":"nm2681217","image":"https://imdb-api.com/images/original/nopicture.jpg","name":"Thomas Fix","asCharacter":"Killer Metal Manas Killer Metal Man"},{"id":"nm1684596","image":"https://imdb-api.com/images/original/nopicture.jpg","name":"Manuel Carrasco","asCharacter":"Man on Radioas Man on Radio"},{"id":"nm1000273","image":"https://imdb-api.com/images/original/MV5BMTcxMDYzOTgyMl5BMl5BanBnXkFtZTYwMjQ2ODYy._V1_Ratio1.0000_AL_.jpg","name":"Deborah Abbott","asCharacter":"Womanas Woman"}],"fullCast":null,"genres":"Short, Sci-Fi","genreList":[{"key":"Short","value":"Short"},{"key":"Sci-Fi","value":"Sci-Fi"}],"companies":"Bowie Film Club","companyList":[{"id":"co0211804","name":"Bowie Film Club"}],"countries":"USA","countryList":[{"key":"USA","value":"USA"}],"languages":"English","languageList":[{"key":"English","value":"English"}],"contentRating":null,"imDbRating":"7.1","imDbRatingVotes":"20","metacriticRating":null,"ratings":null,"wikipedia":null,"posters":null,"images":null,"trailer":null,"boxOffice":{"budget":"","openingWeekendUSA":"","grossUSA":"","cumulativeWorldwideGross":""},"tagline":null,"keywords":"","keywordList":[],"similars":[],"tvSeriesInfo":null,"tvEpisodeInfo":null,"errorMessage":null}
