{"id":"tt1192897","title":"1-2-3 Moskau!","originalTitle":"","fullTitle":"1-2-3 Moskau! (TV Series 2008– )","type":"TVSeries","year":"2008","image":"https://imdb-api.com/images/original/MV5BYWIxMmIzYWItMjQyNC00MWQ4LTgzNzItNzQ3Y2Y0ZTkyZDAyXkEyXkFqcGdeQXVyMTA5NjgzMzY@._V1_Ratio0.6751_AL_.jpg","releaseDate":"2008-03-03","runtimeMins":null,"runtimeStr":null,"plot":"5 Series per 30 Minutes shot in 5 big Metropols in Eastern Europe.","plotLocal":"","plotLocalIsRtl":false,"awards":"","directors":"","directorList":[],"writers":"","writerList":[],"stars":"Katrin Bauerfeind, Henning Wehland, Chuck","starList":[{"id":"nm2607758","name":"Katrin Bauerfeind"},{"id":"nm1111275","name":"Henning Wehland"},{"id":"nm2939435","name":"Chuck"}],"actorList":[{"id":"nm2607758","image":"https://imdb-api.com/images/original/MV5BMTUzMDQyOTg4MF5BMl5BanBnXkFtZTgwMzM1NzAxMTI@._V1_Ratio1.0000_AL_.jpg","name":"Katrin Bauerfeind","asCharacter":"Selfas Self"},{"id":"nm1111275","image":"https://imdb-api.com/images/original/MV5BYmU1YTQ3ZjQtNDBiYy00NTgyLWIyMWYtZWUzODhmZmEyYTBjXkEyXkFqcGdeQXVyMTA2NjY2NzQ0._V1_Ratio1.0000_AL_.jpg","name":"Henning Wehland","asCharacter":"Selfas Self"},{"id":"nm2939435","image":"https://imdb-api.com/images/original/nopicture.jpg","name":"Chuck","asCharacter":"Selfas Self"},{"id":"nm2057901","image":"https://imdb-api.com/images/original/nopicture.jpg","name":"Martins Ritins","asCharacter":"Selfas Self"},{"id":"nm2939193","image":"https://imdb-api.com/images/original/nopicture.jpg","name":"Liena Baklane","asCharacter":"Selfas Self"},{"id":"nm2939222","image":"https://imdb-api.com/images/original/nopicture.jpg","name":"Bango","asCharacter":"Selfas Self"},{"id":"nm2938804","image":"https://imdb-api.com/images/original/nopicture.jpg","name":"Paulius Kilbauskas","asCharacter":"Selfas Self"},{"id":"nm2939307","image":"https://imdb-api.com/images/original/nopicture.jpg","name":"Toomas Lelov","asCharacter":"Selfas Self"},{"id":"nm2938454","image":"https://imdb-api.com/images/original/nopicture.jpg","name":"Evelyn Mikomagi","asCharacter":"Selfas Self"},{"id":"nm2939370","image":"https://imdb-api.com/images/original/nopicture.jpg","name":"Paulis Postazs","asCharacter":"Selfas Self"},{"id":"nm2939421","image":"https://imdb-api.com/images/original/nopicture.jpg","name":"Punk TV","asCharacter":"Themselvesas Themselves"},{"id":"nm2938488","image":"https://imdb-api.com/images/original/nopicture.jpg","name":"Egle Vakarinaite","asCharacter":"Selfas Self"},{"id":"nm2939324","image":"https://imdb-api.com/images/original/nopicture.jpg","name":"Dawid Wolinski","asCharacter":"Selfas Self"},{"id":"nm2939405","image":"https://imdb-api.com/images/original/nopicture.jpg","name":"Nerijus Juska","asCharacter":"Selfas Self"},{"id":"nm2938716","image":"https://imdb-api.com/images/original/nopicture.jpg","name":"Victor Logachov","asCharacter":"Selfas Self"}],"fullCast":null,"genres":"Adventure","genreList":[{"key":"Adventure","value":"Adventure"}],"companies":"MonstaMovies Filmproduktion","companyList":[{"id":"co0176840","name":"MonstaMovies Filmproduktion"}],"countries":"Germany","countryList":[{"key":"Germany","value":"Germany"}],"languages":"English","languageList":[{"key":"English","value":"English"}],"contentRating":null,"imDbRating":"7.3","imDbRatingVotes":"9","metacriticRating":null,"ratings":null,"wikipedia":null,"posters":null,"images":null,"trailer":null,"boxOffice":{"budget":"","openingWeekendUSA":"","grossUSA":"","cumulativeWorldwideGross":""},"tagline":null,"keywords":"moscow russia,wehland,russia,rallye,race","keywordList":["moscow russia","wehland","russia","rallye","race"],"similars":[],"tvSeriesInfo":{"yearEnd":"","creators":"Irina Enders","creatorList":[{"id":"nm2212345","name":"Irina Enders"}],"seasons":["1"]},"tvEpisodeInfo":null,"errorMessage":null}
