{"id":"tt1146527","title":"Bad Medicine in Bangor","originalTitle":"","fullTitle":"Bad Medicine in Bangor (TV Episode 2002)","type":"TVEpisode","year":"2002","image":"https://imdb-api.com/images/original/nopicture.jpg","releaseDate":"2002-01-30","runtimeMins":null,"runtimeStr":null,"plot":"In 1997, Dr. John Malmstrom is found dead of five gunshot wounds in his house, and his wife, Geraldine, is the main suspect when her alibi falls through and the murder weapon is discovered to belong to her family.","plotLocal":"","plotLocalIsRtl":false,"awards":"","directors":"","directorList":[],"writers":"Matt Edens","writerList":[{"id":"nm1206724","name":"Matt Edens"}],"stars":"Paul Winfield","starList":[{"id":"nm0934902","name":"Paul Winfield"}],"actorList":[{"id":"nm0934902","image":"https://imdb-api.com/images/original/MV5BMTI3MDUxMjk1MF5BMl5BanBnXkFtZTYwMTUwNDM2._V1_Ratio1.0000_AL_.jpg","name":"Paul Winfield","asCharacter":"Narratoras Narrator"}],"fullCast":null,"genres":"Crime, Documentary","genreList":[{"key":"Crime","value":"Crime"},{"key":"Documentary","value":"Documentary"}],"companies":"","companyList":[],"countries":"","countryList":[],"languages":"","languageList":[],"contentRating":null,"imDbRating":"7.6","imDbRatingVotes":"6","metacriticRating":null,"ratings":null,"wikipedia":null,"posters":null,"images":null,"trailer":null,"boxOffice":{"budget":"","openingWeekendUSA":"","grossUSA":"","cumulativeWorldwideGross":""},"tagline":null,"keywords":"","keywordList":[],"similars":[],"tvSeriesInfo":null,"tvEpisodeInfo":{"seriesId":"tt0314994","seriesTitle":"City Confidential","seriesFullTitle":"City Confidential (TV Series 1998–2021)","seriesYear":"1998","seriesYearEnd":"2021","seasonNumber":"5","episodeNumber":"13","previousEpisodeId":"tt1159761","nextEpisodeId":"tt1146529"},"errorMessage":null}
