{"id":"tt1223961","title":"Kurak korpe","originalTitle":"","fullTitle":"Kurak korpe (2007)","type":"Movie","year":"2007","image":"https://imdb-api.com/images/original/nopicture.jpg","releaseDate":"2007-09-25","runtimeMins":"97","runtimeStr":"1h 37min","plot":"","plotLocal":"","plotLocalIsRtl":false,"awards":"","directors":"Rustem Abdrashev","directorList":[{"id":"nm0008243","name":"Rustem Abdrashev"}],"writers":"Ermek Tursynov","writerList":[{"id":"nm2992917","name":"Ermek Tursynov"}],"stars":"Valentina Durumbetova, Nurzhuman Ikhtymbaev, Tamara Kosubayeva","starList":[{"id":"nm2992723","name":"Valentina Durumbetova"},{"id":"nm0407521","name":"Nurzhuman Ikhtymbaev"},{"id":"nm0467553","name":"Tamara Kosubayeva"}],"actorList":[{"id":"nm2992723","image":"https://imdb-api.com/images/original/nopicture.jpg","name":"Valentina Durumbetova","asCharacter":""},{"id":"nm0407521","image":"https://imdb-api.com/images/original/MV5BMGI0YmI2YTgtODMyMi00MWE5LThkYjEtZDMzZTk5MTMwMTY4XkEyXkFqcGdeQXVyNjg3MTIwODI@._V1_Ratio1.2429_AL_.jpg","name":"Nurzhuman Ikhtymbaev","asCharacter":""},{"id":"nm0467553","image":"https://imdb-api.com/images/original/nopicture.jpg","name":"Tamara Kosubayeva","asCharacter":""},{"id":"nm2992080","image":"https://imdb-api.com/images/original/nopicture.jpg","name":"Albek Raimbekov","asCharacter":""},{"id":"nm2991839","image":"https://imdb-api.com/images/original/nopicture.jpg","name":"Miras Salmyrza","asCharacter":""}],"fullCast":null,"genres":"","genreList":[],"companies":"Kazakhfilm Studios","companyList":[{"id":"co0036615","name":"Kazakhfilm Studios"}],"countries":"Kazakhstan","countryList":[{"key":"Kazakhstan","value":"Kazakhstan"}],"languages":"Kazakh, Russian","languageList":[{"key":"Kazakh","value":"Kazakh"},{"key":"Russian","value":"Russian"}],"contentRating":null,"imDbRating":null,"imDbRatingVotes":null,"metacriticRating":null,"ratings":null,"wikipedia":null,"posters":null,"images":null,"trailer":null,"boxOffice":{"budget":"","openingWeekendUSA":"","grossUSA":"","cumulativeWorldwideGross":""},"tagline":null,"keywords":"","keywordList":[],"similars":[],"tvSeriesInfo":null,"tvEpisodeInfo":null,"errorMessage":null}
