{"id":"tt1214208","title":"Mudrost","originalTitle":"","fullTitle":"Mudrost (TV Episode 1971)","type":"TVEpisode","year":"1971","image":"https://imdb-api.com/images/original/nopicture.jpg","releaseDate":"1971-06-06","runtimeMins":null,"runtimeStr":null,"plot":"","plotLocal":"","plotLocalIsRtl":false,"awards":"","directors":"Vladan Slijepcevic","directorList":[{"id":"nm0805847","name":"Vladan Slijepcevic"}],"writers":"Aleksandar Popovic","writerList":[{"id":"nm0691403","name":"Aleksandar Popovic"}],"stars":"Zoran Radmilovic, Ruzica Sokic, Slobodan Aligrudic","starList":[{"id":"nm0705707","name":"Zoran Radmilovic"},{"id":"nm0812408","name":"Ruzica Sokic"},{"id":"nm0019609","name":"Slobodan Aligrudic"}],"actorList":[{"id":"nm0705707","image":"https://imdb-api.com/images/original/nopicture.jpg","name":"Zoran Radmilovic","asCharacter":"Zivko Simicas Zivko Simic"},{"id":"nm0812408","image":"https://imdb-api.com/images/original/nopicture.jpg","name":"Ruzica Sokic","asCharacter":"Zivka Simicas Zivka Simic"},{"id":"nm0019609","image":"https://imdb-api.com/images/original/MV5BNTYxODA2NTgyOF5BMl5BanBnXkFtZTgwNTUwMjMyMjE@._V1_Ratio1.5714_AL_.jpg","name":"Slobodan Aligrudic","asCharacter":"Vesa Babicas Vesa Babic"},{"id":"nm0759685","image":"https://imdb-api.com/images/original/MV5BZDc0ZjgxYzMtYjBkYy00ODc2LWJkOWItYzc0NTdiYzlmMzMzXkEyXkFqcGdeQXVyMTc4MzI2NQ@@._V1_Ratio1.0000_AL_.jpg","name":"Ljubisa Samardzic","asCharacter":"Cakan Jankovicas Cakan Jankovic"},{"id":"nm0191005","image":"https://imdb-api.com/images/original/nopicture.jpg","name":"Maja Cuckovic","asCharacter":"Mara Jankovicas Mara Jankovic"},{"id":"nm0865392","image":"https://imdb-api.com/images/original/nopicture.jpg","name":"Bora Todorovic","asCharacter":"Mirko Baturinaas Mirko Baturina"},{"id":"nm0237244","image":"https://imdb-api.com/images/original/MV5BOTc2NjhhNWEtMTU0YS00MDRiLTlmZDMtOWM3NTVmY2I3ODQwXkEyXkFqcGdeQXVyMzI5NDcxNzI@._V1_Ratio1.0000_AL_.jpg","name":"Milena Dravic","asCharacter":"Sladjana Bajicas Sladjana Bajic"},{"id":"nm0587299","image":"https://imdb-api.com/images/original/nopicture.jpg","name":"Tamara Miletic","asCharacter":"Tanja Vuleticas Tanja Vuletic"},{"id":"nm5267700","image":"https://imdb-api.com/images/original/nopicture.jpg","name":"Oliver Djurdjevic","asCharacter":"Dejan Simic ... sinas Dejan Simic ... sin"}],"fullCast":null,"genres":"Comedy, Drama, Romance","genreList":[{"key":"Comedy","value":"Comedy"},{"key":"Drama","value":"Drama"},{"key":"Romance","value":"Romance"}],"companies":"","companyList":[],"countries":"","countryList":[],"languages":"","languageList":[],"contentRating":null,"imDbRating":null,"imDbRatingVotes":null,"metacriticRating":null,"ratings":null,"wikipedia":null,"posters":null,"images":null,"trailer":null,"boxOffice":{"budget":"","openingWeekendUSA":"","grossUSA":"","cumulativeWorldwideGross":""},"tagline":null,"keywords":"","keywordList":[],"similars":[],"tvSeriesInfo":null,"tvEpisodeInfo":{"seriesId":"tt0199199","seriesTitle":"Ceo zivot za godinu dana","seriesFullTitle":"Ceo zivot za godinu dana (TV Series 1971– )","seriesYear":"1971","seriesYearEnd":"","seasonNumber":"1","episodeNumber":"23","previousEpisodeId":"tt1214210","nextEpisodeId":"tt1214211"},"errorMessage":null}
