{"id":"tt1319088","title":"Der gestiefelte Kater","originalTitle":"","fullTitle":"Der gestiefelte Kater (1968)","type":"Movie","year":"1968","image":"https://imdb-api.com/images/original/nopicture.jpg","releaseDate":"1968-03-29","runtimeMins":"PT26M","runtimeStr":"PT26M","plot":"","plotLocal":"","plotLocalIsRtl":false,"awards":"","directors":"Monika Anderson","directorList":[{"id":"nm1645957","name":"Monika Anderson"}],"writers":"Monika Anderson, Klaus Eidam, Jacob Grimm","writerList":[{"id":"nm1645957","name":"Monika Anderson"},{"id":"nm1354936","name":"Klaus Eidam"},{"id":"nm0342278","name":"Jacob Grimm"}],"stars":"Hans Kiessler, Sepp Klose, Siegfried Göhler","starList":[{"id":"nm3190225","name":"Hans Kiessler"},{"id":"nm1189914","name":"Sepp Klose"},{"id":"nm1013054","name":"Siegfried Göhler"}],"actorList":[{"id":"nm3190225","image":"https://imdb-api.com/images/original/nopicture.jpg","name":"Hans Kiessler","asCharacter":"Kateras Kater"},{"id":"nm1189914","image":"https://imdb-api.com/images/original/nopicture.jpg","name":"Sepp Klose","asCharacter":"Müllersohnas Müllersohn"},{"id":"nm1013054","image":"https://imdb-api.com/images/original/nopicture.jpg","name":"Siegfried Göhler","asCharacter":"Schuhmacheras Schuhmacher"},{"id":"nm0472102","image":"https://imdb-api.com/images/original/nopicture.jpg","name":"Lothar Krompholz","asCharacter":"Königas König"},{"id":"nm0255736","image":"https://imdb-api.com/images/original/nopicture.jpg","name":"Thea Elster","asCharacter":"Prinzessinas Prinzessin"},{"id":"nm1778944","image":"https://imdb-api.com/images/original/nopicture.jpg","name":"Manfred Stock","asCharacter":"Zaubereras Zauberer"},{"id":"nm0696729","image":"https://imdb-api.com/images/original/nopicture.jpg","name":"Gina Presgott","asCharacter":"Bäuerinas Bäuerin"}],"fullCast":null,"genres":"Animation, Short","genreList":[{"key":"Animation","value":"Animation"},{"key":"Short","value":"Short"}],"companies":"DEFA-Studio für Trickfilme","companyList":[{"id":"co0114427","name":"DEFA-Studio für Trickfilme"}],"countries":"East Germany","countryList":[{"key":"East Germany","value":"East Germany"}],"languages":"German","languageList":[{"key":"German","value":"German"}],"contentRating":null,"imDbRating":null,"imDbRatingVotes":null,"metacriticRating":null,"ratings":null,"wikipedia":null,"posters":null,"images":null,"trailer":null,"boxOffice":{"budget":"","openingWeekendUSA":"","grossUSA":"","cumulativeWorldwideGross":""},"tagline":null,"keywords":"","keywordList":[],"similars":[],"tvSeriesInfo":null,"tvEpisodeInfo":null,"errorMessage":null}
