{"id":"tt1472805","title":"Me vehkeilijät","originalTitle":"","fullTitle":"Me vehkeilijät (TV Series 1979– )","type":"TVSeries","year":"1979","image":"https://imdb-api.com/images/original/nopicture.jpg","releaseDate":"1979-03-26","runtimeMins":null,"runtimeStr":null,"plot":"","plotLocal":"","plotLocalIsRtl":false,"awards":"","directors":"","directorList":[],"writers":"","writerList":[],"stars":"Ahti Jokinen, Helena Notkonen, Susanna Kekkonen","starList":[{"id":"nm0427035","name":"Ahti Jokinen"},{"id":"nm0636575","name":"Helena Notkonen"},{"id":"nm2626042","name":"Susanna Kekkonen"}],"actorList":[{"id":"nm0427035","image":"https://imdb-api.com/images/original/nopicture.jpg","name":"Ahti Jokinen","asCharacter":""},{"id":"nm0636575","image":"https://imdb-api.com/images/original/nopicture.jpg","name":"Helena Notkonen","asCharacter":""},{"id":"nm2626042","image":"https://imdb-api.com/images/original/nopicture.jpg","name":"Susanna Kekkonen","asCharacter":""},{"id":"nm1620681","image":"https://imdb-api.com/images/original/nopicture.jpg","name":"Jyri Jokinen","asCharacter":""},{"id":"nm2601199","image":"https://imdb-api.com/images/original/nopicture.jpg","name":"Jouni Kekkonen","asCharacter":""},{"id":"nm3542968","image":"https://imdb-api.com/images/original/nopicture.jpg","name":"Olavi Ansamäki","asCharacter":""}],"fullCast":null,"genres":"Documentary","genreList":[{"key":"Documentary","value":"Documentary"}],"companies":"YLE TV1","companyList":[{"id":"co0214258","name":"YLE TV1"}],"countries":"Finland","countryList":[{"key":"Finland","value":"Finland"}],"languages":"Finnish","languageList":[{"key":"Finnish","value":"Finnish"}],"contentRating":null,"imDbRating":null,"imDbRatingVotes":null,"metacriticRating":null,"ratings":null,"wikipedia":null,"posters":null,"images":null,"trailer":null,"boxOffice":{"budget":"","openingWeekendUSA":"","grossUSA":"","cumulativeWorldwideGross":""},"tagline":null,"keywords":"physics,educational","keywordList":["physics","educational"],"similars":[],"tvSeriesInfo":{"yearEnd":"","creators":"Kirsti Tulonen","creatorList":[{"id":"nm1295254","name":"Kirsti Tulonen"}],"seasons":["1"]},"tvEpisodeInfo":null,"errorMessage":null}
