{"id":"tt1416666","title":"Bidoni e il pappagallo","originalTitle":"","fullTitle":"Bidoni e il pappagallo (1914)","type":"Movie","year":"1914","image":"https://imdb-api.com/images/original/nopicture.jpg","releaseDate":null,"runtimeMins":null,"runtimeStr":null,"plot":"","plotLocal":"","plotLocalIsRtl":false,"awards":"","directors":"","directorList":[],"writers":"","writerList":[],"stars":"Primo Cuttica","starList":[{"id":"nm2509095","name":"Primo Cuttica"}],"actorList":[{"id":"nm2509095","image":"https://imdb-api.com/images/original/nopicture.jpg","name":"Primo Cuttica","asCharacter":"Bidonias Bidoni"}],"fullCast":null,"genres":"Short, Comedy","genreList":[{"key":"Short","value":"Short"},{"key":"Comedy","value":"Comedy"}],"companies":"Società Italiana Cines","companyList":[{"id":"co0020261","name":"Società Italiana Cines"}],"countries":"Italy","countryList":[{"key":"Italy","value":"Italy"}],"languages":"None, Italian","languageList":[{"key":"None","value":"None"},{"key":"Italian","value":"Italian"}],"contentRating":null,"imDbRating":null,"imDbRatingVotes":null,"metacriticRating":null,"ratings":null,"wikipedia":null,"posters":null,"images":null,"trailer":null,"boxOffice":{"budget":"","openingWeekendUSA":"","grossUSA":"","cumulativeWorldwideGross":""},"tagline":null,"keywords":"","keywordList":[],"similars":[],"tvSeriesInfo":null,"tvEpisodeInfo":null,"errorMessage":null}
