{"id":"tt1475289","title":"Anselmo","originalTitle":"","fullTitle":"Anselmo (2000)","type":"Movie","year":"2000","image":"https://imdb-api.com/images/original/nopicture.jpg","releaseDate":null,"runtimeMins":"PT10M","runtimeStr":"PT10M","plot":"","plotLocal":"","plotLocalIsRtl":false,"awards":"","directors":"Ignacio Laxalde","directorList":[{"id":"nm1436257","name":"Ignacio Laxalde"}],"writers":"","writerList":[],"stars":"","starList":[],"actorList":[],"fullCast":null,"genres":"Documentary, Short","genreList":[{"key":"Documentary","value":"Documentary"},{"key":"Short","value":"Short"}],"companies":"","companyList":[],"countries":"Argentina","countryList":[{"key":"Argentina","value":"Argentina"}],"languages":"Spanish","languageList":[{"key":"Spanish","value":"Spanish"}],"contentRating":null,"imDbRating":null,"imDbRatingVotes":null,"metacriticRating":null,"ratings":null,"wikipedia":null,"posters":null,"images":null,"trailer":null,"boxOffice":{"budget":"","openingWeekendUSA":"","grossUSA":"","cumulativeWorldwideGross":""},"tagline":null,"keywords":"independent film","keywordList":["independent film"],"similars":[],"tvSeriesInfo":null,"tvEpisodeInfo":null,"errorMessage":null}
