{"id":"tt1547378","title":"Episode #17.42","originalTitle":"","fullTitle":"Episode #17.42 (TV Episode 1988)","type":"TVEpisode","year":"1988","image":"https://imdb-api.com/images/original/nopicture.jpg","releaseDate":"1988-11-08","runtimeMins":null,"runtimeStr":null,"plot":"","plotLocal":"","plotLocalIsRtl":false,"awards":"","directors":"Paul Alter","directorList":[{"id":"nm0022750","name":"Paul Alter"}],"writers":"","writerList":[],"stars":"Kyle Aletter, Bob Barker, Holly Hallstrom","starList":[{"id":"nm0018175","name":"Kyle Aletter"},{"id":"nm0054837","name":"Bob Barker"},{"id":"nm0356775","name":"Holly Hallstrom"}],"actorList":[{"id":"nm0018175","image":"https://imdb-api.com/images/original/nopicture.jpg","name":"Kyle Aletter","asCharacter":"Self - Sub-Modelas Self - Sub-Model"},{"id":"nm0054837","image":"https://imdb-api.com/images/original/MV5BMTg1MzQ1MDMzNV5BMl5BanBnXkFtZTYwMjczMjU0._V1_Ratio1.0000_AL_.jpg","name":"Bob Barker","asCharacter":"Self - Hostas Self - Host"},{"id":"nm0356775","image":"https://imdb-api.com/images/original/MV5BODZlNDVhYTMtZmFhMy00ZmUyLWFkZjMtZGY5MWVkYzcyZWU0XkEyXkFqcGdeQXVyNjUxMjc1OTM@._V1_Ratio1.0000_AL_.jpg","name":"Holly Hallstrom","asCharacter":"Self - Modelas Self - Model"},{"id":"nm0662833","image":"https://imdb-api.com/images/original/nopicture.jpg","name":"Dian Parkinson","asCharacter":"Self - Modelas Self - Model"},{"id":"nm0734509","image":"https://imdb-api.com/images/original/nopicture.jpg","name":"Rod Roddy","asCharacter":"Self - Announceras Self - Announcer"}],"fullCast":null,"genres":"Family, Game-Show, Reality-TV","genreList":[{"key":"Family","value":"Family"},{"key":"Game-Show","value":"Game-Show"},{"key":"Reality-TV","value":"Reality-TV"}],"companies":"Mark Goodson Television Productions, Price Productions","companyList":[{"id":"co0093736","name":"Mark Goodson Television Productions"},{"id":"co0093728","name":"Price Productions"}],"countries":"USA","countryList":[{"key":"USA","value":"USA"}],"languages":"English","languageList":[{"key":"English","value":"English"}],"contentRating":null,"imDbRating":null,"imDbRatingVotes":null,"metacriticRating":null,"ratings":null,"wikipedia":null,"posters":null,"images":null,"trailer":null,"boxOffice":{"budget":"","openingWeekendUSA":"","grossUSA":"","cumulativeWorldwideGross":""},"tagline":null,"keywords":"family game,competition","keywordList":["family game","competition"],"similars":[],"tvSeriesInfo":null,"tvEpisodeInfo":{"seriesId":"tt0068120","seriesTitle":"The Price Is Right","seriesFullTitle":"The Price Is Right (TV Series 1972– )","seriesYear":"1972","seriesYearEnd":"","seasonNumber":"17","episodeNumber":"42","previousEpisodeId":"tt1547377","nextEpisodeId":"tt1547379"},"errorMessage":null}
