{"id":"tt1986026","title":"Hirusagari no jouji","originalTitle":"","fullTitle":"Hirusagari no jouji (2002)","type":"Movie","year":"2002","image":"https://imdb-api.com/images/original/nopicture.jpg","releaseDate":null,"runtimeMins":"PT10M","runtimeStr":"PT10M","plot":"","plotLocal":"","plotLocalIsRtl":false,"awards":"","directors":"Goro Kamio","directorList":[{"id":"nm4616349","name":"Goro Kamio"}],"writers":"","writerList":[],"stars":"","starList":[],"actorList":[],"fullCast":null,"genres":"Short","genreList":[{"key":"Short","value":"Short"}],"companies":"Good Grief","companyList":[{"id":"co0345815","name":"Good Grief"}],"countries":"Japan","countryList":[{"key":"Japan","value":"Japan"}],"languages":"Japanese","languageList":[{"key":"Japanese","value":"Japanese"}],"contentRating":null,"imDbRating":null,"imDbRatingVotes":null,"metacriticRating":null,"ratings":null,"wikipedia":null,"posters":null,"images":null,"trailer":null,"boxOffice":{"budget":"","openingWeekendUSA":"","grossUSA":"","cumulativeWorldwideGross":""},"tagline":null,"keywords":"","keywordList":[],"similars":[],"tvSeriesInfo":null,"tvEpisodeInfo":null,"errorMessage":null}
