{"id":"tt5249124","title":"Toc Show","originalTitle":"","fullTitle":"Toc Show (TV Series 2013– )","type":"TVSeries","year":"2013","image":"https://imdb-api.com/images/original/MV5BYTFjNzJjNjAtMGZlNy00YWFlLWJkYTUtNzJlMjBjYmMwNTYwXkEyXkFqcGdeQXVyMjM4OTczNjQ@._V1_Ratio0.6751_AL_.jpg","releaseDate":"2013-03-04","runtimeMins":null,"runtimeStr":null,"plot":"","plotLocal":"","plotLocalIsRtl":false,"awards":"Awards, 1 nomination","directors":"","directorList":[],"writers":"","writerList":[],"stars":"Juan Carlos Valdivia, Pedro Bastidas, Flavia Fucenecco","starList":[{"id":"nm4623963","name":"Juan Carlos Valdivia"},{"id":"nm7453741","name":"Pedro Bastidas"},{"id":"nm6905560","name":"Flavia Fucenecco"}],"actorList":[{"id":"nm4623963","image":"https://imdb-api.com/images/original/nopicture.jpg","name":"Juan Carlos Valdivia","asCharacter":"Self - Hostas Self - Host"},{"id":"nm7453741","image":"https://imdb-api.com/images/original/nopicture.jpg","name":"Pedro Bastidas","asCharacter":"Self - Panelistas Self - Panelist…"},{"id":"nm6905560","image":"https://imdb-api.com/images/original/nopicture.jpg","name":"Flavia Fucenecco","asCharacter":"Self - Panelistas Self - Panelist"},{"id":"nm7941386","image":"https://imdb-api.com/images/original/nopicture.jpg","name":"Verónica Vieyra","asCharacter":"Self - Panelistas Self - Panelist…"},{"id":"nm6504811","image":"https://imdb-api.com/images/original/nopicture.jpg","name":"Francisca Undurraga","asCharacter":"Self - Panelistas Self - Panelist"},{"id":"nm2802503","image":"https://imdb-api.com/images/original/nopicture.jpg","name":"Yunet Guerra","asCharacter":"Self - Panelistas Self - Panelist…"},{"id":"nm6404952","image":"https://imdb-api.com/images/original/nopicture.jpg","name":"Carola Brethauer","asCharacter":"Self - Hostas Self - Host…"},{"id":"nm1833036","image":"https://imdb-api.com/images/original/nopicture.jpg","name":"Gonzálo Egas","asCharacter":"Self - Panelistas Self - Panelist"},{"id":"nm7574048","image":"https://imdb-api.com/images/original/nopicture.jpg","name":"Paula Bolatti","asCharacter":"Self - Panelistas Self - Panelist…"},{"id":"nm6668319","image":"https://imdb-api.com/images/original/nopicture.jpg","name":"Ruth Gamarra","asCharacter":"Self - Panelistas Self - Panelist"},{"id":"nm7790054","image":"https://imdb-api.com/images/original/nopicture.jpg","name":"Francisca Grandi","asCharacter":"Self - Panelistas Self - Panelist"},{"id":"nm7941390","image":"https://imdb-api.com/images/original/nopicture.jpg","name":"Giselle Gómez Rolón","asCharacter":"Self - Guest Panelistas Self - Guest Panelist…"},{"id":"nm5953499","image":"https://imdb-api.com/images/original/nopicture.jpg","name":"Marcela Brane","asCharacter":"Self - Panelistas Self - Panelist"},{"id":"nm6771597","image":"https://imdb-api.com/images/original/nopicture.jpg","name":"Kika Silva","asCharacter":"Self - Panelistas Self - Panelist…"},{"id":"nm7526377","image":"https://imdb-api.com/images/original/nopicture.jpg","name":"Constanza Solar","asCharacter":"Self - Panelistas Self - Panelist"},{"id":"nm6221191","image":"https://imdb-api.com/images/original/nopicture.jpg","name":"Catalina Vera","asCharacter":"Self - Guestas Self - Guest"},{"id":"nm7790257","image":"https://imdb-api.com/images/original/nopicture.jpg","name":"Dominique Lattimore","asCharacter":"Self - Panelistas Self - Panelist"},{"id":"nm10314543","image":"https://imdb-api.com/images/original/nopicture.jpg","name":"Mery Salas","asCharacter":"Self - Panelistas Self - Panelist"}],"fullCast":null,"genres":"Talk-Show","genreList":[{"key":"Talk-Show","value":"Talk-Show"}],"companies":"Goa Films","companyList":[{"id":"co0172042","name":"Goa Films"}],"countries":"Chile","countryList":[{"key":"Chile","value":"Chile"}],"languages":"Spanish","languageList":[{"key":"Spanish","value":"Spanish"}],"contentRating":null,"imDbRating":"5.3","imDbRatingVotes":"9","metacriticRating":null,"ratings":null,"wikipedia":null,"posters":null,"images":null,"trailer":null,"boxOffice":{"budget":"","openingWeekendUSA":"","grossUSA":"","cumulativeWorldwideGross":""},"tagline":null,"keywords":"made for cable tv,conversation,adult language,adult themes,sexy woman","keywordList":["made for cable tv","conversation","adult language","adult themes","sexy woman"],"similars":[],"tvSeriesInfo":{"yearEnd":"","creators":"Paulo Venegas, Ignacio García","creatorList":[{"id":"nm10009091","name":"Paulo Venegas"},{"id":"nm6168979","name":"Ignacio García"}],"seasons":["2013","2014","2015","2016","2018","2019","2021"]},"tvEpisodeInfo":null,"errorMessage":null}
